MANIFEST.in
README.md
VERSION
setup.cfg
setup.py
aiohttp_baseapi/__init__.py
aiohttp_baseapi/decorators.py
aiohttp_baseapi/errors.py
aiohttp_baseapi/exceptions.py
aiohttp_baseapi/log.py
aiohttp_baseapi/project.py
aiohttp_baseapi/response.py
aiohttp_baseapi.egg-info/PKG-INFO
aiohttp_baseapi.egg-info/SOURCES.txt
aiohttp_baseapi.egg-info/dependency_links.txt
aiohttp_baseapi.egg-info/entry_points.txt
aiohttp_baseapi.egg-info/requires.txt
aiohttp_baseapi.egg-info/top_level.txt
aiohttp_baseapi/data_providers/__init__.py
aiohttp_baseapi/data_providers/base.py
aiohttp_baseapi/data_providers/exceptions.py
aiohttp_baseapi/data_providers/model.py
aiohttp_baseapi/middleware/__init__.py
aiohttp_baseapi/middleware/error_handler.py
aiohttp_baseapi/middleware/params_handler.py
aiohttp_baseapi/project_template/logs/.gitignore
aiohttp_baseapi/project_template/src/__init__.py
aiohttp_baseapi/project_template/src/alembic.ini
aiohttp_baseapi/project_template/src/main.py
aiohttp_baseapi/project_template/src/.meta/packages
aiohttp_baseapi/project_template/src/apps/__init__.py
aiohttp_baseapi/project_template/src/apps/default/__init__.py
aiohttp_baseapi/project_template/src/apps/default/routes.py
aiohttp_baseapi/project_template/src/apps/default/views.py
aiohttp_baseapi/project_template/src/apps/demo/__init__.py
aiohttp_baseapi/project_template/src/apps/demo/data_providers.py
aiohttp_baseapi/project_template/src/apps/demo/models.py
aiohttp_baseapi/project_template/src/apps/demo/routes.py
aiohttp_baseapi/project_template/src/apps/demo/views.py
aiohttp_baseapi/project_template/src/conf/__init__.py
aiohttp_baseapi/project_template/src/conf/defaults.py
aiohttp_baseapi/project_template/src/conf/settings.py
aiohttp_baseapi/project_template/src/core/__init__.py
aiohttp_baseapi/project_template/src/core/app.py
aiohttp_baseapi/project_template/src/core/database.py
aiohttp_baseapi/project_template/src/core/dispatcher.py
aiohttp_baseapi/project_template/src/core/log.py
aiohttp_baseapi/project_template/src/core/middlewares.py
aiohttp_baseapi/project_template/src/core/routes.py
aiohttp_baseapi/project_template/src/core/views.py
aiohttp_baseapi/project_template/src/migrations/env.py
